ansible_collection_path/__init__.py
ansible_collection_path/_version_scm.py
ansible_collection_path/cli.py
ansible_collection_path/collection_path.py
ansible_collection_path-0.5.0.dist-info/licenses/AUTHORS.md
ansible_collection_path-0.5.0.dist-info/licenses/LICENSE
ansible_collection_path-0.5.0.dist-info/METADATA
ansible_collection_path-0.5.0.dist-info/WHEEL
ansible_collection_path-0.5.0.dist-info/entry_points.txt
ansible_collection_path-0.5.0.dist-info/top_level.txt
ansible_collection_path-0.5.0.dist-info/zip-safe
ansible_collection_path-0.5.0.dist-info/RECORD
