Metadata-Version: 2.4
Name: ansible-collection-path
Version: 0.5.0
Summary: Ansible Collection Path Printer
Author-email: Andreas Maier <andreas.r.maier@gmx.de>
Maintainer-email: Andreas Maier <andreas.r.maier@gmx.de>
License: Apache License, Version 2.0
Project-URL: Homepage, https://github.com/andy-maier/ansible-collection-path
Project-URL: Bug Tracker, https://github.com/andy-maier/ansible-collection-path/issues
Project-URL: Source Code, https://github.com/andy-maier/ansible-collection-path
Keywords: ansible,collection
Platform: any
Classifier: License :: OSI Approved :: Apache Software License
Classifier: Development Status :: 5 - Production/Stable
Classifier: Intended Audience :: Information Technology
Classifier: Intended Audience :: System Administrators
Classifier: Topic :: System :: Systems Administration
Classifier: Environment :: Console
Classifier: Operating System :: OS Independent
Classifier: Programming Language :: Python :: 3
Classifier: Programming Language :: Python :: 3.8
Classifier: Programming Language :: Python :: 3.9
Classifier: Programming Language :: Python :: 3.10
Classifier: Programming Language :: Python :: 3.11
Classifier: Programming Language :: Python :: 3.12
Classifier: Programming Language :: Python :: 3.13
Classifier: Programming Language :: Python :: 3.14
Requires-Python: >=3.8
License-File: LICENSE
License-File: AUTHORS.md
Requires-Dist: ansible>=6.0.0
Dynamic: license-file
